CHANGES
LICENSE
MANIFEST.in
README.md
TODO
setup.cfg
setup.py
PyKill.egg-info/PKG-INFO
PyKill.egg-info/SOURCES.txt
PyKill.egg-info/dependency_links.txt
PyKill.egg-info/top_level.txt
docs/PyRIC.pdf
examples/info.py
examples/pentest.py
pykill/__init__.py
pykill/pyw.py
pykill/lib/__init__.py
pykill/lib/libio.py
pykill/lib/libnl.py
pykill/net/__init__.py
pykill/net/genetlink_h.py
pykill/net/if_h.py
pykill/net/netlink_h.py
pykill/net/policy.py
pykill/net/sockios_h.py
pykill/net/wireless/__init__.py
pykill/net/wireless/nl80211_c.py
pykill/net/wireless/nl80211_h.py
pykill/net/wireless/rfkill_h.py
pykill/net/wireless/wlan.py
pykill/nlhelp/__init__.py
pykill/nlhelp/attributes.help
pykill/nlhelp/commands.help
pykill/nlhelp/nlsearch.py
pykill/scripts/__init__.py
pykill/scripts/ouiupdate.py
pykill/utils/__init__.py
pykill/utils/channels.py
pykill/utils/hardware.py
pykill/utils/ouifetch.py
pykill/utils/rfkill.py
pykill/utils/data/oui.txt
tests/__init__.py
tests/pyw.unittest.py
tests/test_wireless.py